graph_pes/__init__.py
graph_pes/atomic_graph.py
graph_pes/graph_pes_model.py
graph_pes/config/shared.py
graph_pes/config/testing.py
graph_pes/config/training-defaults.yaml
graph_pes/config/training.py
graph_pes/data/__init__.py
graph_pes/data/ase_db.py
graph_pes/data/datasets.py
graph_pes/data/loader.py
graph_pes/data/transforms.py
graph_pes/interfaces/__init__.py
graph_pes/interfaces/_mace.py
graph_pes/interfaces/_mattersim.py
graph_pes/interfaces/_orb.py
graph_pes/interfaces/base.py
graph_pes/interfaces/mace_test.py
graph_pes/interfaces/mattersim_test.py
graph_pes/interfaces/orb_test.py
graph_pes/models/__init__.py
graph_pes/models/addition.py
graph_pes/models/eddp.py
graph_pes/models/offsets.py
graph_pes/models/orb.py
graph_pes/models/painn.py
graph_pes/models/pairwise.py
graph_pes/models/schnet.py
graph_pes/models/scripted.py
graph_pes/models/stillinger_weber.py
graph_pes/models/tensornet.py
graph_pes/models/unit_converter.py
graph_pes/models/components/aggregation.py
graph_pes/models/components/distances.py
graph_pes/models/components/scaling.py
graph_pes/models/e3nn/_high_order_CG_coeff.pt
graph_pes/models/e3nn/mace.py
graph_pes/models/e3nn/mace_utils.py
graph_pes/models/e3nn/nequip.py
graph_pes/models/e3nn/utils.py
graph_pes/pair_style/pair_graph_pes.cpp
graph_pes/pair_style/pair_graph_pes.h
graph_pes/scripts/id.py
graph_pes/scripts/resume.py
graph_pes/scripts/test.py
graph_pes/scripts/train.py
graph_pes/scripts/utils.py
graph_pes/training/callbacks.py
graph_pes/training/loss.py
graph_pes/training/opt.py
graph_pes/training/tasks.py
graph_pes/training/utils.py
graph_pes/utils/analysis.py
graph_pes/utils/calculator.py
graph_pes/utils/distributed.py
graph_pes/utils/lammps.py
graph_pes/utils/logger.py
graph_pes/utils/misc.py
graph_pes/utils/nn.py
graph_pes/utils/sampling.py
graph_pes/utils/shift_and_scale.py
graph_pes/utils/threebody.py
graph_pes-0.2.4.dist-info/licenses/LICENSE
graph_pes-0.2.4.dist-info/METADATA
graph_pes-0.2.4.dist-info/WHEEL
graph_pes-0.2.4.dist-info/entry_points.txt
graph_pes-0.2.4.dist-info/top_level.txt
graph_pes-0.2.4.dist-info/RECORD
