Metadata-Version: 2.4
Name: graph-pes
Version: 0.2.4
Summary: Potential Energy Surfaces on Graphs
Author-email: John Gardner <gardner.john97@gmail.com>
License: MIT License
Project-URL: Homepage, https://github.com/jla-gardner/graph-pes
Classifier: License :: OSI Approved :: MIT License
Classifier: Programming Language :: Python
Classifier: Programming Language :: Python :: 3
Requires-Python: >=3.9
License-File: LICENSE
Requires-Dist: torch
Requires-Dist: pytorch-lightning
Requires-Dist: ase
Requires-Dist: numpy
Requires-Dist: rich
Requires-Dist: dacite
Requires-Dist: e3nn==0.4.4
Requires-Dist: scikit-learn
Requires-Dist: locache>=4.0.2
Requires-Dist: load-atoms>=0.3.9
Requires-Dist: wandb
Requires-Dist: data2objects>=0.1.0
Requires-Dist: vesin>=0.3.2
Provides-Extra: test
Requires-Dist: pytest; extra == "test"
Requires-Dist: pytest-cov; extra == "test"
Provides-Extra: docs
Requires-Dist: sphinx; extra == "docs"
Requires-Dist: furo; extra == "docs"
Requires-Dist: nbsphinx; extra == "docs"
Requires-Dist: sphinxext-opengraph; extra == "docs"
Requires-Dist: sphinx-copybutton; extra == "docs"
Requires-Dist: sphinx-design; extra == "docs"
Provides-Extra: publish
Requires-Dist: build; extra == "publish"
Requires-Dist: twine; extra == "publish"
Dynamic: license-file
